catalyst_dkms-0.1.0.dist-info/licenses/LICENSE
src/dkms/__init__.py
src/dkms/classify.py
src/dkms/cli.py
src/dkms/config.py
src/dkms/db.py
src/dkms/embeddings.py
src/dkms/ingest.py
src/dkms/io_detect.py
src/dkms/models.py
src/dkms/pii.py
src/dkms/resources.py
src/dkms/util.py
catalyst_dkms-0.1.0.dist-info/METADATA
catalyst_dkms-0.1.0.dist-info/WHEEL
catalyst_dkms-0.1.0.dist-info/entry_points.txt
catalyst_dkms-0.1.0.dist-info/top_level.txt
catalyst_dkms-0.1.0.dist-info/RECORD
