Metadata-Version: 2.4
Name: catalyst-dkms
Version: 0.1.0
Summary: Domain Knowledge Management System - preprocessing toolset for heterogeneous text ingestion
Author-email: Eric Medlock <eric@example.com>
License: MIT License
Project-URL: Homepage, https://github.com/ericmedlock/Catalyst_DKMS
Project-URL: Repository, https://github.com/ericmedlock/Catalyst_DKMS
Project-URL: Issues, https://github.com/ericmedlock/Catalyst_DKMS/issues
Keywords: nlp,text-processing,embeddings,postgresql,pgvector
Classifier: Development Status :: 4 - Beta
Classifier: Intended Audience :: Developers
Classifier: License :: OSI Approved :: MIT License
Classifier: Programming Language :: Python :: 3
Classifier: Programming Language :: Python :: 3.11
Classifier: Programming Language :: Python :: 3.12
Classifier: Topic :: Scientific/Engineering :: Artificial Intelligence
Classifier: Topic :: Text Processing
Requires-Python: >=3.11
License-File: LICENSE
Requires-Dist: click>=8.1.7
Requires-Dist: pydantic>=2.5.0
Requires-Dist: pydantic-settings>=2.1.0
Requires-Dist: sqlalchemy>=2.0.23
Requires-Dist: psycopg2-binary>=2.9.9
Requires-Dist: pgvector>=0.2.4
Requires-Dist: alembic>=1.13.0
Requires-Dist: pyyaml>=6.0.1
Requires-Dist: structlog>=23.2.0
Provides-Extra: dev
Requires-Dist: pytest>=7.4.3; extra == "dev"
Requires-Dist: pytest-cov>=4.1.0; extra == "dev"
Requires-Dist: ruff>=0.1.8; extra == "dev"
Requires-Dist: black>=23.12.0; extra == "dev"
Requires-Dist: mypy>=1.7.1; extra == "dev"
Requires-Dist: types-pyyaml>=6.0.12.12; extra == "dev"
Dynamic: license-file
